LICENSE
MANIFEST.in
README.rst
buildout.cfg
develop.cfg
pyproject.toml
requirements.txt
setup.py
version.txt
bob/__init__.py
bob.ip.color.egg-info/PKG-INFO
bob.ip.color.egg-info/SOURCES.txt
bob.ip.color.egg-info/dependency_links.txt
bob.ip.color.egg-info/not-zip-safe
bob.ip.color.egg-info/requires.txt
bob.ip.color.egg-info/top_level.txt
bob/ip/__init__.py
bob/ip/color/__init__.py
bob/ip/color/main.cpp
bob/ip/color/rgb_to_gray.cpp
bob/ip/color/rgb_to_hsl.cpp
bob/ip/color/rgb_to_hsv.cpp
bob/ip/color/rgb_to_yuv.cpp
bob/ip/color/test.py
bob/ip/color/utils.cpp
bob/ip/color/utils.h
bob/ip/color/version.cpp
bob/ip/color/cpp/color.cpp
bob/ip/color/data/gray-u8-mids-32bits.hdf5
bob/ip/color/data/gray-u8-mids.hdf5
bob/ip/color/include/bob.ip.color/color.h
bob/ip/color/include/bob.ip.color/config.h
doc/conf.py
doc/index.rst
doc/links.rst
doc/py_api.rst